mentalics/__init__.py
mentalics/explorer.py
mentalics/ns_keyed_archive.py
mentalics/ns_types/__init__.py
mentalics/ns_types/ns_array.py
mentalics/ns_types/ns_data.py
mentalics/ns_types/ns_dictionary.py
mentalics/ns_types/ns_image.py
mentalics/ns_types/ns_mutable_array.py
mentalics/ns_types/ns_mutable_data.py
mentalics/ns_types/ns_mutable_dictionary.py
mentalics/ns_types/ns_point.py
mentalics/ns_types/ns_size.py
mentalics/nscoding.py
mentalics/unarchiver.py
mentalics-0.2.0.dist-info/LICENSE
mentalics-0.2.0.dist-info/METADATA
mentalics-0.2.0.dist-info/WHEEL
mentalics-0.2.0.dist-info/RECORD
