Metadata-Version: 2.1
Name: mentalics
Version: 0.2.0
Summary: Python NSKeyedArchiver explorer, archiver, and dearchiver
Author: Tucker Shea
Author-email: tucker@tuckershea.com
Requires-Python: >=3.9,<4.0
Classifier: License :: OSI Approved :: MIT License
Classifier: Operating System :: OS Independent
Classifier: Programming Language :: Python :: 3
Classifier: Programming Language :: Python :: 3.9
Classifier: Programming Language :: Python :: 3.10
Classifier: Programming Language :: Python :: 3.11
Classifier: Programming Language :: Python :: 3.12
Requires-Dist: setuptools (>=69.0.2,<70.0.0)
